cpskin/__init__.py
cpskin/locales/__init__.py
cpskin/locales/configure.zcml
cpskin/locales/locales/collective.privacy-manual.pot
cpskin/locales/locales/cpskin-generated.pot
cpskin/locales/locales/cpskin-manual.pot
cpskin/locales/locales/cpskin.citizen-manual.pot
cpskin/locales/locales/cpskin.pot
cpskin/locales/locales/plone-manual.pot
cpskin/locales/locales/plone.app.event-manual.pot
cpskin/locales/locales/plone.app.event.pot
cpskin/locales/locales/plone.pot
cpskin/locales/locales/de/LC_MESSAGES/cpskin.citizen.po
cpskin/locales/locales/de/LC_MESSAGES/cpskin.po
cpskin/locales/locales/de/LC_MESSAGES/plone.app.event.po
cpskin/locales/locales/de/LC_MESSAGES/plone.po
cpskin/locales/locales/en/LC_MESSAGES/cpskin.citizen.po
cpskin/locales/locales/en/LC_MESSAGES/cpskin.po
cpskin/locales/locales/en/LC_MESSAGES/plone.app.event.po
cpskin/locales/locales/en/LC_MESSAGES/plone.po
cpskin/locales/locales/es/LC_MESSAGES/cpskin.citizen.po
cpskin/locales/locales/es/LC_MESSAGES/cpskin.po
cpskin/locales/locales/es/LC_MESSAGES/plone.app.event.po
cpskin/locales/locales/es/LC_MESSAGES/plone.po
cpskin/locales/locales/fr/LC_MESSAGES/collective.privacy.po
cpskin/locales/locales/fr/LC_MESSAGES/cpskin.citizen.po
cpskin/locales/locales/fr/LC_MESSAGES/cpskin.po
cpskin/locales/locales/fr/LC_MESSAGES/plone.app.event.po
cpskin/locales/locales/fr/LC_MESSAGES/plone.po
cpskin/locales/locales/fr/LC_MESSAGES/plonelocales.po
cpskin/locales/locales/nl/LC_MESSAGES/cpskin.citizen.po
cpskin/locales/locales/nl/LC_MESSAGES/cpskin.po
cpskin/locales/locales/nl/LC_MESSAGES/plone.app.event.po
cpskin/locales/locales/nl/LC_MESSAGES/plone.po
cpskin.locales-0.5.40.dist-info/DESCRIPTION.rst
cpskin.locales-0.5.40.dist-info/METADATA
cpskin.locales-0.5.40.dist-info/RECORD
cpskin.locales-0.5.40.dist-info/WHEEL
cpskin.locales-0.5.40.dist-info/metadata.json
cpskin.locales-0.5.40.dist-info/top_level.txt
