Metadata-Version: 2.0
Name: cpskin.locales
Version: 0.5.40
Summary: Locales package for cpskin
Home-page: https://github.com/imio/
Author: IMIO
Author-email: support@imio.be
License: gpl
Platform: UNKNOWN
Classifier: Environment :: Web Environment
Classifier: Programming Language :: Python
Classifier: Programming Language :: Python :: 2.7
Classifier: Framework :: Plone
Classifier: Framework :: Plone :: 4.2
Classifier: Framework :: Plone :: 4.3
Requires-Dist: setuptools
Requires-Dist: Plone
